wagtailcharcount/__init__.py
wagtailcharcount/wagtail_hooks.py
wagtailcharcount/static/hallo_charcount.js
wagtail_charcount-0.2.0.dist-info/LICENSE
wagtail_charcount-0.2.0.dist-info/METADATA
wagtail_charcount-0.2.0.dist-info/WHEEL
wagtail_charcount-0.2.0.dist-info/top_level.txt
wagtail_charcount-0.2.0.dist-info/RECORD
