Metadata-Version: 2.1
Name: wagtail-charcount
Version: 0.2.0
Summary: A wagtail character and word counting plugin for RichTextFields.
Home-page: https://github.com/takeflight/wagtail-charcount
Author: Liam Brenner
Author-email: liam@takeflight.com.au
License: BSD License
Classifier: Environment :: Web Environment
Classifier: Intended Audience :: Developers
Classifier: Operating System :: OS Independent
Classifier: Programming Language :: Python
Classifier: Framework :: Django
Classifier: License :: OSI Approved :: BSD License
License-File: LICENSE
Requires-Dist: wagtail >=4.1
